px4test/__init__.py
px4test/__main__.py
px4test/blackbox.py
px4test/config.py
px4test/module.py
px4test/py.typed
px4test-1.0.0a5.dist-info/entry_points.txt
px4test-1.0.0a5.dist-info/WHEEL
px4test-1.0.0a5.dist-info/METADATA
px4test-1.0.0a5.dist-info/RECORD
