Metadata-Version: 2.1
Name: px4test
Version: 1.0.0a5
Summary: Run PX4 falsification tests
License: MIT
Author: Quinn Thibeault
Author-email: quinn.thibeault96@gmail.com
Requires-Python: >=3.7.1,<3.10
Classifier: License :: OSI Approved :: MIT License
Classifier: Programming Language :: Python :: 3
Classifier: Programming Language :: Python :: 3.8
Classifier: Programming Language :: Python :: 3.9
Provides-Extra: docs
Requires-Dist: Sphinx (>=3.5.4,<4.0.0); extra == "docs"
Requires-Dist: click (>=7.1.2,<8.0.0)
Requires-Dist: psy-taliro (>=1.0.0a3,<2.0.0)
Requires-Dist: px4ctl (>=1.0.0a1,<2.0.0)
Requires-Dist: px4stack (>=1.0.0a1,<2.0.0)
Requires-Dist: pyulog (>=0.9.0,<0.10.0)
Requires-Dist: sphinx-autodocgen (>=1.2,<2.0); extra == "docs"
Requires-Dist: sphinx-rtd-theme (>=0.5.2,<0.6.0); extra == "docs"
